pivtools_cli-0.1.0.dist-info/RECORD
pivtools_cli-0.1.0.dist-info/WHEEL
pivtools_cli-0.1.0.dist-info/entry_points.txt
pivtools_cli-0.1.0.dist-info/top_level.txt
pivtools_cli-0.1.0.dist-info/METADATA
pivtools_cli/_build_marker.cpython-38-darwin.so
