Metadata-Version: 2.1
Name: pivtools-cli
Version: 0.1.0
Summary: Command-line interface for PIVTOOLs - Particle Image Velocimetry Tools
License: MIT
Project-URL: Homepage, https://github.com/MTT69/python-PIVTOOLs
Project-URL: Repository, https://github.com/MTT69/python-PIVTOOLs
Project-URL: Issues, https://github.com/MTT69/python-PIVTOOLs/issues
Classifier: Development Status :: 4 - Beta
Classifier: Intended Audience :: Science/Research
Classifier: License :: OSI Approved :: MIT License
Classifier: Operating System :: OS Independent
Classifier: Programming Language :: Python :: 3
Classifier: Programming Language :: Python :: 3.8
Classifier: Programming Language :: Python :: 3.9
Classifier: Programming Language :: Python :: 3.10
Classifier: Programming Language :: Python :: 3.11
Classifier: Programming Language :: Python :: 3.12
Classifier: Topic :: Scientific/Engineering :: Image Processing
Requires-Python: >=3.8
Requires-Dist: pivtools-core>=0.1.0
Requires-Dist: dask-image==2024.5.3
Requires-Dist: numba==0.61.2
Requires-Dist: psutil==6.1.1
Requires-Dist: pytest==8.4.2
Requires-Dist: rawpy==0.25.1
Requires-Dist: scikit-image==0.25.2
Requires-Dist: lvpyio==1.3.1
Requires-Dist: bottleneck==1.6.0
Requires-Dist: scikit-learn==1.7.2
Requires-Dist: threadpoolctl==3.6.0
